elaspic
