Metadata-Version: 1.1
Name: elaspic
Version: 0.1.39
Summary: Ensemble Learning Approach for Stability Prediction of Interface and Core mutations (ELASPIC).
Home-page: https://github.com/kimlaborg/elaspic
Author: kimlab
Author-email: alex.strokach@utoronto.ca
License: UNKNOWN
Platform: UNKNOWN
Classifier: Programming Language :: Python :: 3 :: Only
Classifier: Topic :: Scientific/Engineering :: Bio-Informatics
